quant1x/__init__.py
quant1x/base/__init__.py
quant1x/base/basic.py
quant1x/base/formula.py
quant1x/base/formula_plus.py
quant1x/base/series.py
quant1x/data/__init__.py
quant1x/data/block.py
quant1x/data/futu-basicinfo.py
quant1x/data/quotes.py
quant1x/data/tdx.py
quant1x/data/trade_date.py
quant1x/findpeaks/__init__.py
quant1x/findpeaks/findpeaks.py
quant1x/findpeaks/interpolate.py
quant1x/findpeaks/stats.py
quant1x/findpeaks/union_find.py
quant1x/findpeaks/filters/__init__.py
quant1x/findpeaks/filters/frost.py
quant1x/findpeaks/filters/kuan.py
quant1x/findpeaks/filters/lee.py
quant1x/findpeaks/filters/lee_enhanced.py
quant1x/findpeaks/filters/mean.py
quant1x/findpeaks/filters/median.py
quant1x/formula/__init__.py
quant1x/indicators/__init__.py
quant1x/indicators/ma1x.py
quant1x/strategy/__init__.py
quant1x/strategy/bad_base.py
quant1x/strategy/linear_regression.py
quant1x/util/__init__.py
quant1x/util/font.py
quant1x_formula-0.1.8.dist-info/LICENSE
quant1x_formula-0.1.8.dist-info/METADATA
quant1x_formula-0.1.8.dist-info/WHEEL
quant1x_formula-0.1.8.dist-info/entry_points.txt
quant1x_formula-0.1.8.dist-info/top_level.txt
quant1x_formula-0.1.8.dist-info/RECORD
