Metadata-Version: 2.1
Name: quant1x-formula
Version: 0.1.8
Summary: Quant1X Formula(python)
Home-page: https://gitee.com/quant1x/formula
Author: WangFeng
Author-email: wangfengxy@sina.cn
License: MIT license
Keywords: quant1x formula
Classifier: Development Status :: 2 - Pre-Alpha
Classifier: Intended Audience :: Developers
Classifier: License :: OSI Approved :: MIT License
Classifier: Natural Language :: English
Classifier: Programming Language :: Python :: 3
Classifier: Programming Language :: Python :: 3.8
Classifier: Programming Language :: Python :: 3.9
Classifier: Programming Language :: Python :: 3.10
Classifier: Programming Language :: Python :: 3.11
License-File: LICENSE
Requires-Dist: setuptools ~=68.2.2
Requires-Dist: twine ~=4.0.2
Requires-Dist: wheel ~=0.41.2
Requires-Dist: pymongo ~=4.5.0
Requires-Dist: GitPython ~=3.1.35
Requires-Dist: future ~=0.18.3
Requires-Dist: numpy ~=1.26.0
Requires-Dist: pandas ~=2.1.1
Requires-Dist: PyYAML ~=6.0.1
Requires-Dist: pywin32 ==306
Requires-Dist: Deprecated ~=1.2.13
Requires-Dist: akshare ~=1.8.83
Requires-Dist: mootdx ~=0.10.11
Requires-Dist: requests ~=2.31.0
Requires-Dist: tqdm ~=4.66.1
Requires-Dist: python-dateutil ~=2.8.2
Requires-Dist: futu ~=0.0.1
Requires-Dist: matplotlib ~=3.7.3
Requires-Dist: scikit-learn ~=1.3.0
Requires-Dist: scipy ~=1.11.2
Requires-Dist: caerus ~=0.1.9
Requires-Dist: peakdetect ~=1.1
